{
    "_checkpoint": {
        "global_record": {},
        "progress": [
            1,
            1
        ],
        "records": [
            {
                "timestamp": "Generalization_BadParking_1003-1175",
                "route_id": "Generalization_BadParking_1003-1175",
                "status": "Completed",
                "num_infractions": 3,
                "infractions": {
                    "collisions_layout": [],
                    "collisions_pedestrian": [],
                    "collisions_vehicle": [],
                    "red_light": [],
                    "stop_infraction": [],
                    "outside_route_lanes": [],
                    "min_speed_infractions": [
                        "Average speed is 90.22% of the surrounding traffic's one",
                        "Average speed is 99.35% of the surrounding traffic's one",
                        "Average speed is 87.37% of the surrounding traffic's one"
                    ],
                    "yield_emergency_vehicle_infractions": [],
                    "scenario_timeouts": [],
                    "route_dev": [],
                    "vehicle_blocked": [],
                    "route_timeout": []
                },
                "scores": {
                    "score_route": 100,
                    "score_penalty": 0.932061,
                    "score_composed": 93.206062
                },
                "meta": {
                    "route_length": 0.0,
                    "duration_game": 0.0,
                    "duration_system": 0.0
                },
                "save_name": "Generalization_BadParking_1003-1175"
            }
        ]
    }
}
