{
    "_checkpoint": {
        "global_record": {},
        "progress": [
            1,
            1
        ],
        "records": [
            {
                "timestamp": "RouteScenario_30_rep0_Town13_Generalization_RightConstruction_1090_05_13_04_55_55",
                "route_id": "RouteScenario_30_rep0",
                "status": "Completed",
                "num_infractions": 1,
                "infractions": {
                    "collisions_layout": [],
                    "collisions_pedestrian": [],
                    "collisions_vehicle": [],
                    "red_light": [],
                    "stop_infraction": [],
                    "outside_route_lanes": [],
                    "min_speed_infractions": [
                        "Average speed is 99.91% of the surrounding traffic's one"
                    ],
                    "yield_emergency_vehicle_infractions": [],
                    "scenario_timeouts": [],
                    "route_dev": [],
                    "vehicle_blocked": [],
                    "route_timeout": []
                },
                "scores": {
                    "score_route": 100,
                    "score_penalty": 0.99973,
                    "score_composed": 99.973
                },
                "meta": {
                    "route_length": 298.698,
                    "duration_game": 42.8,
                    "duration_system": 440.571
                },
                "save_name": "RouteScenario_30_rep0_Town13_Generalization_RightConstruction_1090_05_13_04_55_55"
            }
        ]
    }
}
